gmail_attachment_dl/__init__.py
gmail_attachment_dl/auth.py
gmail_attachment_dl/config.py
gmail_attachment_dl/downloader.py
gmail_attachment_dl/main.py
gmail_attachment_dl/matcher.py
gmail_attachment_dl-0.1.0.dist-info/licenses/LICENSE
gmail_attachment_dl-0.1.0.dist-info/METADATA
gmail_attachment_dl-0.1.0.dist-info/WHEEL
gmail_attachment_dl-0.1.0.dist-info/entry_points.txt
gmail_attachment_dl-0.1.0.dist-info/top_level.txt
gmail_attachment_dl-0.1.0.dist-info/RECORD
