Metadata-Version: 2.4
Name: gmail-attachment-dl
Version: 0.1.0
Summary: Gmail attachment downloader with regex filtering support
Author: kakehashi
License: MIT License
Project-URL: Homepage, https://github.com/kakehashi-inc/gmail-attachment-dl
Project-URL: Repository, https://github.com/kakehashi-inc/gmail-attachment-dl.git
Project-URL: Issues, https://github.com/kakehashi-inc/gmail-attachment-dl/issues
Keywords: gmail,attachment,download,email,automation
Classifier: Development Status :: 4 - Beta
Classifier: Intended Audience :: Developers
Classifier: License :: OSI Approved :: MIT License
Classifier: Operating System :: OS Independent
Classifier: Programming Language :: Python :: 3
Classifier: Programming Language :: Python :: 3.10
Classifier: Programming Language :: Python :: 3.11
Classifier: Programming Language :: Python :: 3.12
Classifier: Topic :: Communications :: Email
Classifier: Topic :: Software Development :: Libraries :: Python Modules
Requires-Python: >=3.8
License-File: LICENSE
Requires-Dist: google-auth>=2.16.0
Requires-Dist: google-auth-oauthlib>=1.0.0
Requires-Dist: google-auth-httplib2>=0.1.0
Requires-Dist: google-api-python-client>=2.100.0
Requires-Dist: cryptography>=41.0.0
Requires-Dist: click>=8.1.0
Provides-Extra: dev
Requires-Dist: pylint; extra == "dev"
Requires-Dist: pylint-plugin-utils; extra == "dev"
Requires-Dist: black; extra == "dev"
Provides-Extra: build
Requires-Dist: build>=1.0.0; extra == "build"
Requires-Dist: twine>=5.0.0; extra == "build"
Requires-Dist: wheel>=0.42.0; extra == "build"
Dynamic: license-file
